aliyunsdkgwlb/__init__.py
aliyunsdkgwlb/endpoint.py
aliyunsdkgwlb/request/__init__.py
aliyunsdkgwlb/request/v20240415/AddServersToServerGroupRequest.py
aliyunsdkgwlb/request/v20240415/CreateListenerRequest.py
aliyunsdkgwlb/request/v20240415/CreateLoadBalancerRequest.py
aliyunsdkgwlb/request/v20240415/CreateServerGroupRequest.py
aliyunsdkgwlb/request/v20240415/DeleteListenerRequest.py
aliyunsdkgwlb/request/v20240415/DeleteLoadBalancerRequest.py
aliyunsdkgwlb/request/v20240415/DeleteServerGroupRequest.py
aliyunsdkgwlb/request/v20240415/DescribeRegionsRequest.py
aliyunsdkgwlb/request/v20240415/DescribeZonesRequest.py
aliyunsdkgwlb/request/v20240415/GetListenerAttributeRequest.py
aliyunsdkgwlb/request/v20240415/GetListenerHealthStatusRequest.py
aliyunsdkgwlb/request/v20240415/GetLoadBalancerAttributeRequest.py
aliyunsdkgwlb/request/v20240415/ListListenersRequest.py
aliyunsdkgwlb/request/v20240415/ListLoadBalancersRequest.py
aliyunsdkgwlb/request/v20240415/ListServerGroupServersRequest.py
aliyunsdkgwlb/request/v20240415/ListServerGroupsRequest.py
aliyunsdkgwlb/request/v20240415/ListTagResourcesRequest.py
aliyunsdkgwlb/request/v20240415/MoveResourceGroupRequest.py
aliyunsdkgwlb/request/v20240415/RemoveServersFromServerGroupRequest.py
aliyunsdkgwlb/request/v20240415/TagResourcesRequest.py
aliyunsdkgwlb/request/v20240415/UntagResourcesRequest.py
aliyunsdkgwlb/request/v20240415/UpdateListenerAttributeRequest.py
aliyunsdkgwlb/request/v20240415/UpdateLoadBalancerAttributeRequest.py
aliyunsdkgwlb/request/v20240415/UpdateLoadBalancerZonesRequest.py
aliyunsdkgwlb/request/v20240415/UpdateServerGroupAttributeRequest.py
aliyunsdkgwlb/request/v20240415/__init__.py
aliyun_python_sdk_gwlb-1.0.2.dist-info/LICENSE
aliyun_python_sdk_gwlb-1.0.2.dist-info/METADATA
aliyun_python_sdk_gwlb-1.0.2.dist-info/WHEEL
aliyun_python_sdk_gwlb-1.0.2.dist-info/top_level.txt
aliyun_python_sdk_gwlb-1.0.2.dist-info/RECORD
